MANIFEST.in
README.rst
pycodcif.c
pycodcif.i
setup.py
./__init__.py
./pycodcif.py
pycodcif.egg-info/PKG-INFO
pycodcif.egg-info/SOURCES.txt
pycodcif.egg-info/dependency_links.txt
pycodcif.egg-info/top_level.txt
src/components/codcif/cif.c
src/components/codcif/cif.h
src/components/codcif/cif2_grammar.tab.c
src/components/codcif/cif2_grammar.tab.h
src/components/codcif/cif2_grammar_y.h
src/components/codcif/cif2_lexer.c
src/components/codcif/cif2_lexer.h
src/components/codcif/cif_compiler.c
src/components/codcif/cif_compiler.h
src/components/codcif/cif_grammar.tab.c
src/components/codcif/cif_grammar.tab.h
src/components/codcif/cif_grammar_flex.c
src/components/codcif/cif_grammar_flex.h
src/components/codcif/cif_grammar_y.h
src/components/codcif/cif_lex_buffer.c
src/components/codcif/cif_lex_buffer.h
src/components/codcif/cif_lexer.c
src/components/codcif/cif_lexer.h
src/components/codcif/cif_options.c
src/components/codcif/cif_options.h
src/components/codcif/ciflist.c
src/components/codcif/ciflist.h
src/components/codcif/cifmessage.c
src/components/codcif/cifmessage.h
src/components/codcif/ciftable.c
src/components/codcif/ciftable.h
src/components/codcif/cifvalue.c
src/components/codcif/cifvalue.h
src/components/codcif/common.c
src/components/codcif/common.h
src/components/codcif/datablock.c
src/components/codcif/datablock.h
src/components/codcif/version.h
src/components/codcif/yy.h
src/externals/cexceptions/allocx.c
src/externals/cexceptions/allocx.h
src/externals/cexceptions/cexceptions.c
src/externals/cexceptions/cexceptions.h
src/externals/cexceptions/cxprintf.c
src/externals/cexceptions/cxprintf.h
src/externals/cexceptions/stdiox.c
src/externals/cexceptions/stdiox.h
src/externals/cexceptions/stringx.c
src/externals/cexceptions/stringx.h