Metadata-Version: 2.1
Name: pycodcif
Version: 3.0.1
Summary: COD CIF parser
Home-page: http://wiki.crystallography.net/cod-tools/CIF-parser
Author: COD development team
Author-email: grazulis@ibt.lt
Maintainer: Andrius Merkys
Maintainer-email: andrius.merkys@gmail.com
License: LGPLv3
Project-URL: Source, https://github.com/cod-developers/cod-tools
Platform: UNKNOWN
